{
  "hash": "c5dacf0ab0fb4e83adc21125114abc2e",
  "result": {
    "engine": "knitr",
    "markdown": "---\ntitle: \"07 - DC and DR for each region per time (Figure 2)\"\nsubtitle: \"07_V_scatterplot_Fig2.qmd\"\nformat: html\neval: true\n---\n\n\n:::callout-note\nThe final figure presented in the manuscript is further edited with\n    the aid o inkscape software\n:::\n\n\n# Domestic contribution (DC) and Domestic retention (DR) for all countries\n\nReading libraries\n\n\n::: {.cell}\n\n```{.r .cell-code}\nlibrary(dplyr)    # Data manipulation\n```\n\n::: {.cell-output .cell-output-stderr}\n\n```\n\nAnexando pacote: 'dplyr'\n```\n\n\n:::\n\n::: {.cell-output .cell-output-stderr}\n\n```\nOs seguintes objetos são mascarados por 'package:stats':\n\n    filter, lag\n```\n\n\n:::\n\n::: {.cell-output .cell-output-stderr}\n\n```\nOs seguintes objetos são mascarados por 'package:base':\n\n    intersect, setdiff, setequal, union\n```\n\n\n:::\n\n```{.r .cell-code}\nlibrary(here)     # File path management\n```\n\n::: {.cell-output .cell-output-stderr}\n\n```\nhere() starts at C:/Users/gabri/OneDrive/Manuscritos/NBT_code_data\n```\n\n\n:::\n\n```{.r .cell-code}\nlibrary(tidyr)    # Data tidying\nlibrary(ggplot2)  # Data visualization\nlibrary(scales)   # Scale transformations and labels\n```\n\n::: {.cell-output .cell-output-stderr}\n\n```\nWarning: pacote 'scales' foi compilado no R versão 4.4.1\n```\n\n\n:::\n\n```{.r .cell-code}\nlibrary(ggarrow)  # Adding arrows to ggplot\n```\n:::\n\n\n\nHere we combined two metrics, DC and DR by time and regions, to express the\n    changes of NBTs distribution for each of these regions. \n    This is aimed to be the Figure 02 in the manuscript. The Figure 2 in the main\n    text was further edited in inkscape to better acomodate the arrows and \n    include the quadrant information in the first plot.\n\n\n\n::: {.cell}\n\n```{.r .cell-code}\n# Data from 01_C_data_preparation.qmd\n\nflow_period_region_prop <- readr::read_csv(here::here(\"data\", \"processed\", \"flow_period_region_prop.csv\"))\n```\n\n::: {.cell-output .cell-output-stderr}\n\n```\nRows: 42 Columns: 9\n── Column specification ────────────────────────────────────────────────────────\nDelimiter: \",\"\nchr (2): region_type, region_museum\ndbl (7): period, n, total_period_region_type, total_period_region_museum, to...\n\nℹ Use `spec()` to retrieve the full column specification for this data.\nℹ Specify the column types or set `show_col_types = FALSE` to quiet this message.\n```\n\n\n:::\n:::\n\n\nAdd lag values for visualization\n\n\n::: {.cell}\n\n```{.r .cell-code}\nflow_period_region_prop_lag <- flow_period_region_prop |>\n  dplyr::group_by(region_type) |>\n  dplyr::mutate(new_DC = dplyr::lag(prop_DC),\n                new_DR = dplyr::lag(prop_DR)) |> \n  dplyr::ungroup()\n```\n:::\n\n\n## Figure 2 - Scatterplot\n\n\n::: {.cell}\n\n```{.r .cell-code}\nflow_period_region_prop_lag |>\n  dplyr::filter(dplyr::if_all(c(prop_DC, prop_DR, \n                                new_DC, new_DR), \n                              ~ . != 0 | is.na(.))) |> \n  ggplot(aes(x = prop_DC, y = prop_DR, fill = region_type))+\n  geom_hline(yintercept = 0.5, linetype = \"dashed\")+\n  geom_vline(xintercept = 0.5, linetype = \"dashed\")+\n  geom_arrow_segment(\n    aes(x = new_DC, xend = prop_DC,\n        y = new_DR, yend = prop_DR),\n    color = \"grey\",\n    arrow_head = NULL,\n    arrow_mid  = arrow_head_wings(offset = 30,\n                                  inset = 60),\n    resect_head = 2,\n    resect_fins = 2\n  )+\n  geom_point(\n    shape = 21,\n    size = 2.5\n  )+\n  geom_point(\n    aes(x = new_DC ,\n        y = new_DR),\n    alpha = 0.5,\n    shape = 21,\n    size = 2.5\n  )+\n  facet_wrap(.~period,axes = \"all\",\n             axis.labels = \"margins\"\n              )+\n  scale_fill_manual(\n    values = c(\n      \"Europe & Central Asia\" = \"#E64B35FF\",\n      \"East Asia & Pacific\" = \"#4DBBD5FF\",\n      \"North America\" = \"#3C5488FF\",\n      \"South Asia\" = \"#B09C85FF\",\n      \"Latin America & Caribbean\" = \"#00A087FF\",\n      \"Sub-Saharan Africa\" = \"#F39B7FFF\",\n      \"Middle East & North Africa\" = \"#8491B4FF\"\n    )\n  )+\n  scale_x_continuous(\n    labels = scales::label_percent(),\n    expand = expansion(mult = c(0.05, 0))\n  )+\n  scale_y_continuous(\n    labels = scales::label_percent(),\n    expand = expansion(mult = c(0.05, 0))\n  )+\n  theme_classic()+\n  theme(\n    strip.background = element_rect(fill = NA, color = NA),\n    strip.text = element_text(face = \"bold\"),\n    legend.position = \"none\",\n    plot.background = element_blank(),\n    panel.spacing = unit(5, \"pt\"),\n    panel.spacing.x = unit(15, \"pt\"),\n    plot.margin = margin(5,15,5,5,\"pt\"),\n    axis.line = element_line(lineend = \"round\"),\n    axis.text = element_text(color = \"black\"),\n    axis.ticks = element_line(color = \"black\")\n  )+\n  coord_cartesian(xlim = c(0,1),\n                  ylim = c(0,1),\n                  clip = \"off\")\n```\n\n::: {.cell-output .cell-output-stderr}\n\n```\nWarning: Removed 2 rows containing missing values or values outside the scale range\n(`geom_arrow_segment()`).\n```\n\n\n:::\n\n::: {.cell-output .cell-output-stderr}\n\n```\nWarning: Removed 2 rows containing missing values or values outside the scale range\n(`geom_point()`).\n```\n\n\n:::\n\n::: {.cell-output-display}\n![](07_V_scatterplot_Fig2_files/figure-html/unnamed-chunk-4-1.png){width=672}\n:::\n\n```{.r .cell-code}\nggsave(filename = here::here(\"output\", \"figures\", \"Fig2_DC_DR.png\"), \n       width = 8, height = 5)\n```\n\n::: {.cell-output .cell-output-stderr}\n\n```\nWarning: Removed 2 rows containing missing values or values outside the scale range\n(`geom_arrow_segment()`).\nRemoved 2 rows containing missing values or values outside the scale range\n(`geom_point()`).\n```\n\n\n:::\n:::",
    "supporting": [
      "07_V_scatterplot_Fig2_files"
    ],
    "filters": [
      "rmarkdown/pagebreak.lua"
    ],
    "includes": {},
    "engineDependencies": {},
    "preserve": {},
    "postProcess": true
  }
}